LICENSE
MANIFEST.in
README.md
requirements.txt
setup.cfg
setup.py
sgmarkets_api_xsf_rollbox/__init__.py
sgmarkets_api_xsf_rollbox/__meta__.py
sgmarkets_api_xsf_rollbox/_dashboard.py
sgmarkets_api_xsf_rollbox/_obj_from_dict.py
sgmarkets_api_xsf_rollbox/_plot.py
sgmarkets_api_xsf_rollbox/_util.py
sgmarkets_api_xsf_rollbox/endpoint.py
sgmarkets_api_xsf_rollbox/info.py
sgmarkets_api_xsf_rollbox/request_rollbox_analysis.py
sgmarkets_api_xsf_rollbox/request_rollbox_analysis_types.py
sgmarkets_api_xsf_rollbox/request_rollbox_relative_roll.py
sgmarkets_api_xsf_rollbox/request_rollbox_underlyings.py
sgmarkets_api_xsf_rollbox/request_rollbox_underlyings_with_rolls.py
sgmarkets_api_xsf_rollbox/response_rollbox_analysis.py
sgmarkets_api_xsf_rollbox/response_rollbox_analysis_types.py
sgmarkets_api_xsf_rollbox/response_rollbox_relative_roll.py
sgmarkets_api_xsf_rollbox/response_rollbox_underlyings.py
sgmarkets_api_xsf_rollbox/response_rollbox_underlyings_with_rolls.py
sgmarkets_api_xsf_rollbox.egg-info/PKG-INFO
sgmarkets_api_xsf_rollbox.egg-info/SOURCES.txt
sgmarkets_api_xsf_rollbox.egg-info/dependency_links.txt
sgmarkets_api_xsf_rollbox.egg-info/not-zip-safe
sgmarkets_api_xsf_rollbox.egg-info/requires.txt
sgmarkets_api_xsf_rollbox.egg-info/top_level.txt
sgmarkets_api_xsf_rollbox/img/jupyter-logo.png
sgmarkets_api_xsf_rollbox/img/sg-logo.png
sgmarkets_api_xsf_rollbox/markdown/info.md