Metadata-Version: 1.1
Name: sgmarkets-api-xsf-rollbox
Version: 0.2.0
Summary: sgmarket api xsf ROLLBOX helper
Home-page: https://gitlab.com/sgmarkets/sgmarkets-api-xsf-rollbox
Author: sgmarkets
Author-email: olivier.borderies@gmail.com
License: MIT
Download-URL: https://gitlab.com/sgmarkets/sgmarkets-api-xsf-rollbox/repository/archive.tar.gz?ref=0.2.0
Keywords: sgmarkets,api,xsf,rollbox
Platform: UNKNOWN
Classifier: Development Status :: 4 - Beta
Classifier: License :: OSI Approved :: MIT License
Classifier: Programming Language :: Python :: 3.5
Classifier: Programming Language :: Python :: 3.6
